kaos_storages/__init__.py
kaos_storages/fields.py
kaos_storages/s3.py
kaos_storages/settings.py
tests/__init__.py
tests/test_fields.py
dj_kaos_storages-0.1.1.dist-info/LICENSE
dj_kaos_storages-0.1.1.dist-info/METADATA
dj_kaos_storages-0.1.1.dist-info/WHEEL
dj_kaos_storages-0.1.1.dist-info/top_level.txt
dj_kaos_storages-0.1.1.dist-info/RECORD
