Metadata-Version: 2.1
Name: dj-kaos-storages
Version: 0.1.1
Summary: A set of django media storage classes for different use cases such as private file storage on S3
Home-page: https://github.com/kaoslabsinc/dj-kaos-storages
Author: Kaos Labs Inc.
Author-email: keyvan@keyvanm.com
License: BSD-3-Clause
Keywords: django,storages,s3,boto,django-storages,kaos
Platform: UNKNOWN
Classifier: Environment :: Web Environment
Classifier: Framework :: Django
Classifier: Framework :: Django :: 3.2
Classifier: Intended Audience :: Developers
Classifier: License :: OSI Approved :: BSD License
Classifier: Operating System :: OS Independent
Classifier: Programming Language :: Python
Classifier: Programming Language :: Python :: 3
Classifier: Programming Language :: Python :: 3 :: Only
Classifier: Programming Language :: Python :: 3.7
Classifier: Programming Language :: Python :: 3.8
Classifier: Programming Language :: Python :: 3.9
Classifier: Topic :: Internet :: WWW/HTTP
Classifier: Topic :: Internet :: WWW/HTTP :: Dynamic Content
License-File: LICENSE
Requires-Dist: django (>=3.2)
Requires-Dist: django-storages[boto3] (~=1.11.1)
Provides-Extra: test
Requires-Dist: tox ; extra == 'test'
Requires-Dist: pytest-django ; extra == 'test'
Requires-Dist: pytest-pythonpath ; extra == 'test'
